a_selenium_screenshots_all_elements/LICENSE
a_selenium_screenshots_all_elements/README.MD
a_selenium_screenshots_all_elements/__init__.py
a_selenium_screenshots_all_elements/requirements.txt
a_selenium_screenshots_all_elements/thirdparty.json
a_selenium_screenshots_all_elements-0.10.dist-info/LICENSE.rst
a_selenium_screenshots_all_elements-0.10.dist-info/METADATA
a_selenium_screenshots_all_elements-0.10.dist-info/WHEEL
a_selenium_screenshots_all_elements-0.10.dist-info/top_level.txt
a_selenium_screenshots_all_elements-0.10.dist-info/RECORD
