Metadata-Version: 2.1
Name: a-selenium-screenshots-all-elements
Version: 0.10
Summary: Takes a screenshot of every element on a site
Home-page: https://github.com/hansalemaos/a_selenium_screenshots_all_elements
Author: Johannes Fischer
Author-email: <aulasparticularesdealemaosp@gmail.com>
License: MIT
Keywords: Selenium,elements,screenshot
Classifier: Development Status :: 4 - Beta
Classifier: Programming Language :: Python :: 3 :: Only
Classifier: Programming Language :: Python :: 3.9
Classifier: Topic :: Scientific/Engineering :: Visualization
Classifier: Topic :: Software Development :: Libraries :: Python Modules
Classifier: Topic :: Text Editors :: Text Processing
Classifier: Topic :: Text Processing :: General
Classifier: Topic :: Text Processing :: Indexing
Classifier: Topic :: Text Processing :: Filters
Classifier: Topic :: Utilities
License-File: LICENSE.rst
Requires-Dist: a-cv-imwrite-imread-plus
Requires-Dist: a-selenium2df
Requires-Dist: a-selenium-screenshot-whole-page
Requires-Dist: check-if-nan
Requires-Dist: numpy
Requires-Dist: opencv-python
Requires-Dist: pandas
Requires-Dist: PILasOPENCV
Requires-Dist: regex
Requires-Dist: selenium
